qiskit_qasm2/__init__.py
qiskit_qasm2/VERSION
qiskit_qasm2/parse.py
qiskit_qasm2/core.cpython-310-darwin.so
qiskit_qasm2-0.5.3.1.dist-info/RECORD
qiskit_qasm2-0.5.3.1.dist-info/LICENSE
qiskit_qasm2-0.5.3.1.dist-info/WHEEL
qiskit_qasm2-0.5.3.1.dist-info/top_level.txt
qiskit_qasm2-0.5.3.1.dist-info/METADATA
