Metadata-Version: 2.1
Name: qiskit-qasm2
Version: 0.5.3.1
Summary: Importer for parsing OpenQASM 2 strings into Qiskit circuits
Home-page: https://github.com/jakelishman/qiskit-qasm2
Author: Jake Lishman
License: Apache 2.0 License
Project-URL: Bug Tracker, https://github.com/jakelishman/qiskit-qasm2/issues
Project-URL: Documentation, https://jakelishman.github.io/qiskit-qasm2
Project-URL: Source Code, https://github.com/jakelishman/qiskit-qasm2
License-File: LICENSE
Requires-Dist: qiskit-terra >=0.21.0
Requires-Dist: typing-extensions >=4.1.0
Provides-Extra: all
